{
  "victini": {
    "availableEarly": false,
    "isBaseForm": true,
    "isLegendary": false,
    "games": [
      "black",
      "black-2",
      "white",
      "white-2"
    ],
    "isFinalForm": true,
    "evolves_from": null,
    "id": 494
  },
  "snivy": {
    "availableEarly": false,
    "isBaseForm": true,
    "isLegendary": false,
    "games": [
      "black",
      "black-2",
      "white",
      "white-2"
    ],
    "isFinalForm": false,
    "evolves_from": null,
    "id": 495
  },
  "servine": {
    "availableEarly": false,
    "isBaseForm": false,
    "isLegendary": false,
    "games": [
      "black",
      "black-2",
      "white",
      "white-2"
    ],
    "isFinalForm": false,
    "evolves_from": "snivy",
    "id": 496
  },
  "serperior": {
    "availableEarly": false,
    "isBaseForm": false,
    "isLegendary": false,
    "games": [
      "black",
      "black-2",
      "white",
      "white-2"
    ],
    "isFinalForm": true,
    "evolves_from": "servine",
    "id": 497
  },
  "tepig": {
    "availableEarly": false,
    "isBaseForm": true,
    "isLegendary": false,
    "games": [
      "black",
      "black-2",
      "white",
      "white-2"
    ],
    "isFinalForm": false,
    "evolves_from": null,
    "id": 498
  },
  "pignite": {
    "availableEarly": false,
    "isBaseForm": false,
    "isLegendary": false,
    "games": [
      "black",
      "black-2",
      "white",
      "white-2"
    ],
    "isFinalForm": false,
    "evolves_from": "tepig",
    "id": 499
  },
  "emboar": {
    "availableEarly": false,
    "isBaseForm": false,
    "isLegendary": false,
    "games": [
      "black",
      "black-2",
      "white",
      "white-2"
    ],
    "isFinalForm": true,
    "evolves_from": "pignite",
    "id": 500
  },
  "oshawott": {
    "availableEarly": false,
    "isBaseForm": true,
    "isLegendary": false,
    "games": [
      "black",
      "black-2",
      "white",
      "white-2",
      "legendsarceus"
    ],
    "isFinalForm": false,
    "evolves_from": null,
    "id": 501
  },
  "dewott": {
    "availableEarly": false,
    "isBaseForm": false,
    "isLegendary": false,
    "games": [
      "black",
      "black-2",
      "white",
      "white-2",
      "legendsarceus"
    ],
    "isFinalForm": false,
    "evolves_from": "oshawott",
    "id": 502
  },
  "samurott": {
    "availableEarly": false,
    "isBaseForm": false,
    "isLegendary": false,
    "games": [
      "black",
      "black-2",
      "white",
      "white-2",
      "legendsarceus"
    ],
    "isFinalForm": true,
    "evolves_from": "dewott",
    "id": 503
  },
  "patrat": {
    "availableEarly": false,
    "isBaseForm": true,
    "isLegendary": false,
    "games": [
      "black",
      "black-2",
      "white",
      "white-2"
    ],
    "isFinalForm": false,
    "evolves_from": null,
    "id": 504
  },
  "watchog": {
    "availableEarly": false,
    "isBaseForm": false,
    "isLegendary": false,
    "games": [
      "black",
      "black-2",
      "white",
      "white-2"
    ],
    "isFinalForm": true,
    "evolves_from": "patrat",
    "id": 505
  },
  "lillipup": {
    "availableEarly": false,
    "isBaseForm": true,
    "isLegendary": false,
    "games": [
      "black",
      "black-2",
      "white",
      "white-2",
      "ultrasun",
      "ultramoon"
    ],
    "isFinalForm": false,
    "evolves_from": null,
    "id": 506
  },
  "herdier": {
    "availableEarly": false,
    "isBaseForm": false,
    "isLegendary": false,
    "games": [
      "black",
      "black-2",
      "white",
      "white-2",
      "ultrasun",
      "ultramoon"
    ],
    "isFinalForm": false,
    "evolves_from": "lillipup",
    "id": 507
  },
  "stoutland": {
    "availableEarly": false,
    "isBaseForm": false,
    "isLegendary": false,
    "games": [
      "black",
      "black-2",
      "white",
      "white-2",
      "ultrasun",
      "ultramoon"
    ],
    "isFinalForm": true,
    "evolves_from": "herdier",
    "id": 508
  },
  "purrloin": {
    "availableEarly": false,
    "isBaseForm": true,
    "isLegendary": false,
    "games": [
      "black",
      "black-2",
      "white",
      "white-2",
      "sword",
      "shield"
    ],
    "isFinalForm": false,
    "evolves_from": null,
    "id": 509
  },
  "liepard": {
    "availableEarly": false,
    "isBaseForm": false,
    "isLegendary": false,
    "games": [
      "black",
      "black-2",
      "white",
      "white-2",
      "sword",
      "shield"
    ],
    "isFinalForm": true,
    "evolves_from": "purrloin",
    "id": 510
  },
  "pansage": {
    "availableEarly": false,
    "isBaseForm": true,
    "isLegendary": false,
    "games": [
      "black",
      "black-2",
      "white",
      "white-2"
    ],
    "isFinalForm": false,
    "evolves_from": null,
    "id": 511
  },
  "simisage": {
    "availableEarly": false,
    "isBaseForm": false,
    "isLegendary": false,
    "games": [
      "black",
      "black-2",
      "white",
      "white-2"
    ],
    "isFinalForm": true,
    "evolves_from": "pansage",
    "id": 512
  },
  "pansear": {
    "availableEarly": false,
    "isBaseForm": true,
    "isLegendary": false,
    "games": [
      "black",
      "black-2",
      "white",
      "white-2"
    ],
    "isFinalForm": false,
    "evolves_from": null,
    "id": 513
  },
  "simisear": {
    "availableEarly": false,
    "isBaseForm": false,
    "isLegendary": false,
    "games": [
      "black",
      "black-2",
      "white",
      "white-2"
    ],
    "isFinalForm": true,
    "evolves_from": "pansear",
    "id": 514
  },
  "panpour": {
    "availableEarly": false,
    "isBaseForm": true,
    "isLegendary": false,
    "games": [
      "black",
      "black-2",
      "white",
      "white-2"
    ],
    "isFinalForm": false,
    "evolves_from": null,
    "id": 515
  },
  "simipour": {
    "availableEarly": false,
    "isBaseForm": false,
    "isLegendary": false,
    "games": [
      "black",
      "black-2",
      "white",
      "white-2"
    ],
    "isFinalForm": true,
    "evolves_from": "panpour",
    "id": 516
  },
  "munna": {
    "availableEarly": false,
    "isBaseForm": true,
    "isLegendary": false,
    "games": [
      "black",
      "black-2",
      "white",
      "white-2",
      "sword",
      "shield"
    ],
    "isFinalForm": false,
    "evolves_from": null,
    "id": 517
  },
  "musharna": {
    "availableEarly": false,
    "isBaseForm": false,
    "isLegendary": false,
    "games": [
      "black",
      "black-2",
      "white",
      "white-2",
      "sword",
      "shield"
    ],
    "isFinalForm": true,
    "evolves_from": "munna",
    "id": 518
  },
  "pidove": {
    "availableEarly": false,
    "isBaseForm": true,
    "isLegendary": false,
    "games": [
      "black",
      "black-2",
      "white",
      "white-2",
      "sword",
      "shield"
    ],
    "isFinalForm": false,
    "evolves_from": null,
    "id": 519
  },
  "tranquill": {
    "availableEarly": false,
    "isBaseForm": false,
    "isLegendary": false,
    "games": [
      "black",
      "black-2",
      "white",
      "white-2",
      "sword",
      "shield"
    ],
    "isFinalForm": false,
    "evolves_from": "pidove",
    "id": 520
  },
  "unfezant": {
    "availableEarly": false,
    "isBaseForm": false,
    "isLegendary": false,
    "games": [
      "black",
      "black-2",
      "white",
      "white-2",
      "sword",
      "shield"
    ],
    "isFinalForm": true,
    "evolves_from": "tranquill",
    "id": 521
  },
  "blitzle": {
    "availableEarly": true,
    "isBaseForm": true,
    "isLegendary": false,
    "games": [
      "black",
      "black-2",
      "white",
      "white-2"
    ],
    "isFinalForm": false,
    "evolves_from": null,
    "id": 522
  },
  "zebstrika": {
    "availableEarly": false,
    "isBaseForm": false,
    "isLegendary": false,
    "games": [
      "black",
      "black-2",
      "white",
      "white-2"
    ],
    "isFinalForm": true,
    "evolves_from": "blitzle",
    "id": 523
  },
  "roggenrola": {
    "availableEarly": false,
    "isBaseForm": true,
    "isLegendary": false,
    "games": [
      "black",
      "black-2",
      "white",
      "white-2",
      "sword",
      "shield",
      "ultrasun",
      "ultramoon"
    ],
    "isFinalForm": false,
    "evolves_from": null,
    "id": 524
  },
  "boldore": {
    "availableEarly": false,
    "isBaseForm": false,
    "isLegendary": false,
    "games": [
      "black",
      "black-2",
      "white",
      "white-2",
      "sword",
      "shield",
      "ultrasun",
      "ultramoon"
    ],
    "isFinalForm": false,
    "evolves_from": "roggenrola",
    "id": 525
  },
  "gigalith": {
    "availableEarly": false,
    "isBaseForm": false,
    "isLegendary": false,
    "games": [
      "black",
      "black-2",
      "white",
      "white-2",
      "sword",
      "shield",
      "ultrasun",
      "ultramoon"
    ],
    "isFinalForm": true,
    "evolves_from": "boldore",
    "id": 526
  },
  "woobat": {
    "availableEarly": false,
    "isBaseForm": true,
    "isLegendary": false,
    "games": [
      "black",
      "black-2",
      "white",
      "white-2",
      "sword",
      "shield"
    ],
    "isFinalForm": false,
    "evolves_from": null,
    "id": 527
  },
  "swoobat": {
    "availableEarly": false,
    "isBaseForm": false,
    "isLegendary": false,
    "games": [
      "black",
      "black-2",
      "white",
      "white-2",
      "sword",
      "shield"
    ],
    "isFinalForm": true,
    "evolves_from": "woobat",
    "id": 528
  },
  "drilbur": {
    "availableEarly": false,
    "isBaseForm": true,
    "isLegendary": false,
    "games": [
      "black",
      "black-2",
      "white",
      "white-2",
      "sword",
      "shield"
    ],
    "isFinalForm": false,
    "evolves_from": null,
    "id": 529
  },
  "excadrill": {
    "availableEarly": false,
    "isBaseForm": false,
    "isLegendary": false,
    "games": [
      "black",
      "black-2",
      "white",
      "white-2",
      "sword",
      "shield"
    ],
    "isFinalForm": true,
    "evolves_from": "drilbur",
    "id": 530
  },
  "audino": {
    "availableEarly": false,
    "isBaseForm": true,
    "isLegendary": false,
    "games": [
      "black",
      "black-2",
      "white",
      "white-2"
    ],
    "isFinalForm": false,
    "evolves_from": null,
    "id": 531
  },
  "timburr": {
    "availableEarly": false,
    "isBaseForm": true,
    "isLegendary": false,
    "games": [
      "black",
      "black-2",
      "white",
      "white-2",
      "sword",
      "shield"
    ],
    "isFinalForm": false,
    "evolves_from": null,
    "id": 532
  },
  "gurdurr": {
    "availableEarly": false,
    "isBaseForm": false,
    "isLegendary": false,
    "games": [
      "black",
      "black-2",
      "white",
      "white-2",
      "sword",
      "shield"
    ],
    "isFinalForm": false,
    "evolves_from": "timburr",
    "id": 533
  },
  "conkeldurr": {
    "availableEarly": false,
    "isBaseForm": false,
    "isLegendary": false,
    "games": [
      "black",
      "black-2",
      "white",
      "white-2",
      "sword",
      "shield"
    ],
    "isFinalForm": true,
    "evolves_from": "gurdurr",
    "id": 534
  },
  "tympole": {
    "availableEarly": false,
    "isBaseForm": true,
    "isLegendary": false,
    "games": [
      "black",
      "black-2",
      "white",
      "white-2",
      "sword",
      "shield"
    ],
    "isFinalForm": false,
    "evolves_from": null,
    "id": 535
  },
  "palpitoad": {
    "availableEarly": false,
    "isBaseForm": false,
    "isLegendary": false,
    "games": [
      "black",
      "black-2",
      "white",
      "white-2",
      "sword",
      "shield"
    ],
    "isFinalForm": false,
    "evolves_from": "tympole",
    "id": 536
  },
  "seismitoad": {
    "availableEarly": false,
    "isBaseForm": false,
    "isLegendary": false,
    "games": [
      "black",
      "black-2",
      "white",
      "white-2",
      "sword",
      "shield"
    ],
    "isFinalForm": true,
    "evolves_from": "palpitoad",
    "id": 537
  },
  "throh": {
    "availableEarly": false,
    "isBaseForm": true,
    "isLegendary": false,
    "games": [
      "black",
      "black-2",
      "white",
      "white-2",
      "sword",
      "shield"
    ],
    "isFinalForm": false,
    "evolves_from": null,
    "id": 538
  },
  "sawk": {
    "availableEarly": false,
    "isBaseForm": false,
    "isLegendary": false,
    "games": [
      "black",
      "black-2",
      "white",
      "white-2",
      "sword",
      "shield"
    ],
    "isFinalForm": true,
    "evolves_from": "throh",
    "id": 539
  },
  "sewaddle": {
    "availableEarly": true,
    "isBaseForm": true,
    "isLegendary": false,
    "games": [
      "black",
      "black-2",
      "white",
      "white-2"
    ],
    "isFinalForm": false,
    "evolves_from": null,
    "id": 540
  },
  "swadloon": {
    "availableEarly": false,
    "isBaseForm": false,
    "isLegendary": false,
    "games": [
      "black",
      "black-2",
      "white",
      "white-2"
    ],
    "isFinalForm": false,
    "evolves_from": "sewaddle",
    "id": 541
  },
  "leavanny": {
    "availableEarly": false,
    "isBaseForm": false,
    "isLegendary": false,
    "games": [
      "black",
      "black-2",
      "white",
      "white-2"
    ],
    "isFinalForm": true,
    "evolves_from": "swadloon",
    "id": 542
  },
  "venipede": {
    "availableEarly": true,
    "isBaseForm": true,
    "isLegendary": false,
    "games": [
      "black",
      "black-2",
      "white",
      "white-2"
    ],
    "isFinalForm": false,
    "evolves_from": null,
    "id": 543
  },
  "whirlipede": {
    "availableEarly": false,
    "isBaseForm": false,
    "isLegendary": false,
    "games": [
      "black",
      "black-2",
      "white",
      "white-2"
    ],
    "isFinalForm": false,
    "evolves_from": "venipede",
    "id": 544
  },
  "scolipede": {
    "availableEarly": false,
    "isBaseForm": false,
    "isLegendary": false,
    "games": [
      "black",
      "black-2",
      "white",
      "white-2"
    ],
    "isFinalForm": true,
    "evolves_from": "whirlipede",
    "id": 545
  },
  "cottonee": {
    "availableEarly": true,
    "isBaseForm": true,
    "isLegendary": false,
    "games": [
      "black",
      "black-2",
      "white",
      "white-2",
      "sword",
      "shield",
      "ultrasun",
      "ultramoon"
    ],
    "isFinalForm": false,
    "evolves_from": null,
    "id": 546
  },
  "whimsicott": {
    "availableEarly": false,
    "isBaseForm": false,
    "isLegendary": false,
    "games": [
      "black",
      "black-2",
      "white",
      "white-2",
      "sword",
      "shield",
      "ultrasun",
      "ultramoon"
    ],
    "isFinalForm": true,
    "evolves_from": "cottonee",
    "id": 547
  },
  "petilil": {
    "availableEarly": true,
    "isBaseForm": true,
    "isLegendary": false,
    "games": [
      "black",
      "black-2",
      "white",
      "white-2",
      "scarlet",
      "violet",
      "ultrasun",
      "ultramoon",
      "legendsarceus"
    ],
    "isFinalForm": false,
    "evolves_from": null,
    "id": 548
  },
  "lilligant": {
    "availableEarly": false,
    "isBaseForm": false,
    "isLegendary": false,
    "games": [
      "black",
      "black-2",
      "white",
      "white-2",
      "scarlet",
      "violet",
      "ultrasun",
      "ultramoon",
      "legendsarceus"
    ],
    "isFinalForm": true,
    "evolves_from": "petilil",
    "id": 549
  },
  "basculin": {
    "availableEarly": true,
    "isBaseForm": true,
    "isLegendary": false,
    "games": [
      "scarlet",
      "violet",
      "sword",
      "shield",
      "ultrasun",
      "ultramoon",
      "legendsarceus"
    ],
    "isFinalForm": false,
    "evolves_from": null,
    "id": 550
  },
  "sandile": {
    "availableEarly": true,
    "isBaseForm": true,
    "isLegendary": false,
    "games": [
      "black",
      "black-2",
      "white",
      "white-2",
      "scarlet",
      "violet",
      "ultrasun",
      "ultramoon"
    ],
    "isFinalForm": false,
    "evolves_from": null,
    "id": 551
  },
  "krokorok": {
    "availableEarly": false,
    "isBaseForm": false,
    "isLegendary": false,
    "games": [
      "black",
      "black-2",
      "white",
      "white-2",
      "scarlet",
      "violet",
      "ultrasun",
      "ultramoon"
    ],
    "isFinalForm": false,
    "evolves_from": "sandile",
    "id": 552
  },
  "krookodile": {
    "availableEarly": false,
    "isBaseForm": false,
    "isLegendary": false,
    "games": [
      "black",
      "black-2",
      "white",
      "white-2",
      "scarlet",
      "violet",
      "ultrasun",
      "ultramoon"
    ],
    "isFinalForm": true,
    "evolves_from": "krokorok",
    "id": 553
  },
  "darumaka": {
    "availableEarly": true,
    "isBaseForm": true,
    "isLegendary": false,
    "games": [
      "black",
      "black-2",
      "white",
      "white-2",
      "sword",
      "shield"
    ],
    "isFinalForm": false,
    "evolves_from": null,
    "id": 554
  },
  "darmanitan": {
    "availableEarly": false,
    "isBaseForm": false,
    "isLegendary": false,
    "games": [
      "sword",
      "shield"
    ],
    "isFinalForm": true,
    "evolves_from": "darumaka",
    "id": 555
  },
  "maractus": {
    "availableEarly": false,
    "isBaseForm": false,
    "isLegendary": false,
    "games": [
      "black",
      "black-2",
      "white",
      "white-2",
      "sword",
      "shield"
    ],
    "isFinalForm": true,
    "evolves_from": null,
    "id": 556
  },
  "dwebble": {
    "availableEarly": false,
    "isBaseForm": true,
    "isLegendary": false,
    "games": [
      "black",
      "black-2",
      "white",
      "white-2",
      "sword",
      "shield"
    ],
    "isFinalForm": false,
    "evolves_from": null,
    "id": 557
  },
  "crustle": {
    "availableEarly": false,
    "isBaseForm": false,
    "isLegendary": false,
    "games": [
      "black",
      "black-2",
      "white",
      "white-2",
      "sword",
      "shield"
    ],
    "isFinalForm": true,
    "evolves_from": "dwebble",
    "id": 558
  },
  "scraggy": {
    "availableEarly": false,
    "isBaseForm": true,
    "isLegendary": false,
    "games": [
      "black",
      "black-2",
      "white",
      "white-2",
      "sword",
      "shield",
      "ultrasun",
      "ultramoon"
    ],
    "isFinalForm": false,
    "evolves_from": null,
    "id": 559
  },
  "scrafty": {
    "availableEarly": false,
    "isBaseForm": false,
    "isLegendary": false,
    "games": [
      "black",
      "black-2",
      "white",
      "white-2",
      "sword",
      "shield",
      "ultrasun",
      "ultramoon"
    ],
    "isFinalForm": true,
    "evolves_from": "scraggy",
    "id": 560
  },
  "sigilyph": {
    "availableEarly": false,
    "isBaseForm": true,
    "isLegendary": false,
    "games": [
      "black",
      "black-2",
      "white",
      "white-2",
      "sword",
      "shield"
    ],
    "isFinalForm": false,
    "evolves_from": null,
    "id": 561
  },
  "yamask": {
    "availableEarly": false,
    "isBaseForm": true,
    "isLegendary": false,
    "games": [
      "black",
      "black-2",
      "white",
      "white-2",
      "sword",
      "shield"
    ],
    "isFinalForm": false,
    "evolves_from": null,
    "id": 562
  },
  "cofagrigus": {
    "availableEarly": false,
    "isBaseForm": false,
    "isLegendary": false,
    "games": [
      "black",
      "black-2",
      "white",
      "white-2",
      "sword",
      "shield"
    ],
    "isFinalForm": true,
    "evolves_from": "yamask",
    "id": 563
  },
  "tirtouga": {
    "availableEarly": false,
    "isBaseForm": true,
    "isLegendary": false,
    "games": [
      "black",
      "black-2",
      "white",
      "white-2",
      "ultrasun",
      "ultramoon"
    ],
    "isFinalForm": false,
    "evolves_from": null,
    "id": 564
  },
  "carracosta": {
    "availableEarly": false,
    "isBaseForm": false,
    "isLegendary": false,
    "games": [
      "black",
      "black-2",
      "white",
      "white-2",
      "ultrasun",
      "ultramoon"
    ],
    "isFinalForm": true,
    "evolves_from": "tirtouga",
    "id": 565
  },
  "archen": {
    "availableEarly": false,
    "isBaseForm": true,
    "isLegendary": false,
    "games": [
      "black",
      "black-2",
      "white",
      "white-2",
      "ultrasun",
      "ultramoon"
    ],
    "isFinalForm": false,
    "evolves_from": null,
    "id": 566
  },
  "archaeops": {
    "availableEarly": false,
    "isBaseForm": false,
    "isLegendary": false,
    "games": [],
    "isFinalForm": true,
    "evolves_from": "archen",
    "id": 567
  },
  "trubbish": {
    "availableEarly": true,
    "isBaseForm": true,
    "isLegendary": false,
    "games": [
      "black",
      "black-2",
      "white",
      "white-2",
      "sword",
      "shield",
      "ultrasun",
      "ultramoon"
    ],
    "isFinalForm": false,
    "evolves_from": null,
    "id": 568
  },
  "garbodor": {
    "availableEarly": false,
    "isBaseForm": false,
    "isLegendary": false,
    "games": [
      "black",
      "black-2",
      "white",
      "white-2",
      "sword",
      "shield",
      "ultrasun",
      "ultramoon"
    ],
    "isFinalForm": true,
    "evolves_from": "trubbish",
    "id": 569
  },
  "zorua": {
    "availableEarly": false,
    "isBaseForm": true,
    "isLegendary": false,
    "games": [
      "black",
      "black-2",
      "white",
      "white-2",
      "scarlet",
      "violet",
      "ultrasun",
      "ultramoon",
      "legendsarceus"
    ],
    "isFinalForm": false,
    "evolves_from": null,
    "id": 570
  },
  "zorark": {
    "availableEarly": false,
    "isBaseForm": false,
    "isLegendary": false,
    "games": [],
    "isFinalForm": true,
    "evolves_from": "zorua",
    "id": 571
  },
  "minccino": {
    "availableEarly": false,
    "isBaseForm": true,
    "isLegendary": false,
    "games": [
      "black",
      "black-2",
      "white",
      "white-2",
      "sword",
      "shield",
      "ultrasun",
      "ultramoon"
    ],
    "isFinalForm": false,
    "evolves_from": null,
    "id": 572
  },
  "cinccino": {
    "availableEarly": false,
    "isBaseForm": false,
    "isLegendary": false,
    "games": [
      "black",
      "black-2",
      "white",
      "white-2",
      "sword",
      "shield",
      "ultrasun",
      "ultramoon"
    ],
    "isFinalForm": true,
    "evolves_from": "minccino",
    "id": 573
  },
  "gothita": {
    "availableEarly": false,
    "isBaseForm": true,
    "isLegendary": false,
    "games": [
      "black",
      "black-2",
      "white",
      "white-2",
      "scarlet",
      "violet",
      "sword",
      "shield"
    ],
    "isFinalForm": false,
    "evolves_from": null,
    "id": 574
  },
  "gothorita": {
    "availableEarly": false,
    "isBaseForm": false,
    "isLegendary": false,
    "games": [
      "black",
      "black-2",
      "white",
      "white-2",
      "scarlet",
      "violet",
      "sword",
      "shield"
    ],
    "isFinalForm": false,
    "evolves_from": "gothita",
    "id": 575
  },
  "gothitelle": {
    "availableEarly": false,
    "isBaseForm": false,
    "isLegendary": false,
    "games": [
      "black",
      "black-2",
      "white",
      "white-2",
      "scarlet",
      "violet",
      "sword",
      "shield"
    ],
    "isFinalForm": true,
    "evolves_from": "gothorita",
    "id": 576
  },
  "solosis": {
    "availableEarly": false,
    "isBaseForm": true,
    "isLegendary": false,
    "games": [
      "black",
      "black-2",
      "white",
      "white-2",
      "sword",
      "shield"
    ],
    "isFinalForm": false,
    "evolves_from": null,
    "id": 577
  },
  "duosion": {
    "availableEarly": false,
    "isBaseForm": false,
    "isLegendary": false,
    "games": [
      "black",
      "black-2",
      "white",
      "white-2",
      "sword",
      "shield"
    ],
    "isFinalForm": false,
    "evolves_from": "solosis",
    "id": 578
  },
  "reuniclus": {
    "availableEarly": false,
    "isBaseForm": false,
    "isLegendary": false,
    "games": [
      "black",
      "black-2",
      "white",
      "white-2",
      "sword",
      "shield"
    ],
    "isFinalForm": true,
    "evolves_from": "duosion",
    "id": 579
  },
  "ducklett": {
    "availableEarly": true,
    "isBaseForm": true,
    "isLegendary": false,
    "games": [
      "black",
      "black-2",
      "white",
      "white-2"
    ],
    "isFinalForm": false,
    "evolves_from": null,
    "id": 580
  },
  "swanna": {
    "availableEarly": false,
    "isBaseForm": false,
    "isLegendary": false,
    "games": [
      "black",
      "black-2",
      "white",
      "white-2"
    ],
    "isFinalForm": true,
    "evolves_from": "ducklett",
    "id": 581
  },
  "vanillite": {
    "availableEarly": false,
    "isBaseForm": true,
    "isLegendary": false,
    "games": [
      "black",
      "black-2",
      "white",
      "white-2",
      "sword",
      "shield",
      "ultrasun",
      "ultramoon"
    ],
    "isFinalForm": false,
    "evolves_from": null,
    "id": 582
  },
  "vanillish": {
    "availableEarly": false,
    "isBaseForm": false,
    "isLegendary": false,
    "games": [
      "black",
      "black-2",
      "white",
      "white-2",
      "sword",
      "shield",
      "ultrasun",
      "ultramoon"
    ],
    "isFinalForm": false,
    "evolves_from": "vanillite",
    "id": 583
  },
  "vanilluxe": {
    "availableEarly": false,
    "isBaseForm": false,
    "isLegendary": false,
    "games": [
      "black",
      "black-2",
      "white",
      "white-2",
      "sword",
      "shield",
      "ultrasun",
      "ultramoon"
    ],
    "isFinalForm": true,
    "evolves_from": "vanillish",
    "id": 584
  },
  "deerling": {
    "availableEarly": false,
    "isBaseForm": true,
    "isLegendary": false,
    "games": [
      "scarlet",
      "violet"
    ],
    "isFinalForm": false,
    "evolves_from": null,
    "id": 585
  },
  "sawsbuck": {
    "availableEarly": false,
    "isBaseForm": false,
    "isLegendary": false,
    "games": [
      "scarlet",
      "violet"
    ],
    "isFinalForm": true,
    "evolves_from": "deerling",
    "id": 586
  },
  "emolga": {
    "availableEarly": false,
    "isBaseForm": true,
    "isLegendary": false,
    "games": [
      "black",
      "black-2",
      "white",
      "white-2",
      "ultrasun",
      "ultramoon"
    ],
    "isFinalForm": false,
    "evolves_from": null,
    "id": 587
  },
  "karrablast": {
    "availableEarly": false,
    "isBaseForm": true,
    "isLegendary": false,
    "games": [
      "black",
      "black-2",
      "white",
      "white-2",
      "sword",
      "shield"
    ],
    "isFinalForm": false,
    "evolves_from": null,
    "id": 588
  },
  "escavalier": {
    "availableEarly": false,
    "isBaseForm": false,
    "isLegendary": false,
    "games": [
      "black",
      "black-2",
      "white",
      "white-2",
      "sword",
      "shield"
    ],
    "isFinalForm": true,
    "evolves_from": "karrablast",
    "id": 589
  },
  "foongus": {
    "availableEarly": false,
    "isBaseForm": true,
    "isLegendary": false,
    "games": [
      "black",
      "black-2",
      "white",
      "white-2",
      "scarlet",
      "violet"
    ],
    "isFinalForm": false,
    "evolves_from": null,
    "id": 590
  },
  "amoonguss": {
    "availableEarly": false,
    "isBaseForm": false,
    "isLegendary": false,
    "games": [
      "black",
      "black-2",
      "white",
      "white-2",
      "scarlet",
      "violet"
    ],
    "isFinalForm": true,
    "evolves_from": "foongus",
    "id": 591
  },
  "frillish": {
    "availableEarly": false,
    "isBaseForm": true,
    "isLegendary": false,
    "games": [
      "black",
      "black-2",
      "white",
      "white-2",
      "sword",
      "shield",
      "ultrasun",
      "ultramoon"
    ],
    "isFinalForm": false,
    "evolves_from": null,
    "id": 592
  },
  "jellicent": {
    "availableEarly": false,
    "isBaseForm": false,
    "isLegendary": false,
    "games": [
      "black",
      "black-2",
      "white",
      "white-2",
      "sword",
      "shield",
      "ultrasun",
      "ultramoon"
    ],
    "isFinalForm": true,
    "evolves_from": "frillish",
    "id": 593
  },
  "alomomola": {
    "availableEarly": false,
    "isBaseForm": true,
    "isLegendary": false,
    "games": [
      "black",
      "black-2",
      "white",
      "white-2",
      "scarlet",
      "violet",
      "ultrasun",
      "ultramoon"
    ],
    "isFinalForm": true,
    "evolves_from": null,
    "id": 594
  },
  "joltik": {
    "availableEarly": false,
    "isBaseForm": true,
    "isLegendary": false,
    "games": [
      "black",
      "black-2",
      "white",
      "white-2",
      "sword",
      "shield"
    ],
    "isFinalForm": false,
    "evolves_from": null,
    "id": 595
  },
  "galvantula": {
    "availableEarly": false,
    "isBaseForm": false,
    "isLegendary": false,
    "games": [
      "black",
      "black-2",
      "white",
      "white-2",
      "sword",
      "shield"
    ],
    "isFinalForm": true,
    "evolves_from": "joltik",
    "id": 596
  },
  "ferroseed": {
    "availableEarly": false,
    "isBaseForm": true,
    "isLegendary": false,
    "games": [
      "black",
      "black-2",
      "white",
      "white-2",
      "sword",
      "shield"
    ],
    "isFinalForm": false,
    "evolves_from": null,
    "id": 597
  },
  "ferrothorn": {
    "availableEarly": false,
    "isBaseForm": false,
    "isLegendary": false,
    "games": [
      "black",
      "black-2",
      "white",
      "white-2",
      "sword",
      "shield"
    ],
    "isFinalForm": true,
    "evolves_from": "ferroseed",
    "id": 598
  },
  "klink": {
    "availableEarly": false,
    "isBaseForm": true,
    "isLegendary": false,
    "games": [
      "black",
      "black-2",
      "white",
      "white-2",
      "sword",
      "shield"
    ],
    "isFinalForm": false,
    "evolves_from": null,
    "id": 599
  },
  "klang": {
    "availableEarly": false,
    "isBaseForm": false,
    "isLegendary": false,
    "games": [
      "black",
      "black-2",
      "white",
      "white-2",
      "sword",
      "shield"
    ],
    "isFinalForm": false,
    "evolves_from": "klink",
    "id": 600
  },
  "klinklang": {
    "availableEarly": false,
    "isBaseForm": false,
    "isLegendary": false,
    "games": [
      "black",
      "black-2",
      "white",
      "white-2",
      "sword",
      "shield"
    ],
    "isFinalForm": true,
    "evolves_from": "klang",
    "id": 601
  },
  "tynamo": {
    "availableEarly": false,
    "isBaseForm": true,
    "isLegendary": false,
    "games": [
      "black",
      "black-2",
      "white",
      "white-2",
      "scarlet",
      "violet"
    ],
    "isFinalForm": false,
    "evolves_from": null,
    "id": 602
  },
  "eelektrik": {
    "availableEarly": false,
    "isBaseForm": false,
    "isLegendary": false,
    "games": [
      "black",
      "black-2",
      "white",
      "white-2",
      "scarlet",
      "violet"
    ],
    "isFinalForm": false,
    "evolves_from": "tynamo",
    "id": 603
  },
  "eelektross": {
    "availableEarly": false,
    "isBaseForm": false,
    "isLegendary": false,
    "games": [
      "black",
      "black-2",
      "white",
      "white-2",
      "scarlet",
      "violet"
    ],
    "isFinalForm": true,
    "evolves_from": "eelektrik",
    "id": 604
  },
  "elgyem": {
    "availableEarly": false,
    "isBaseForm": true,
    "isLegendary": false,
    "games": [
      "black",
      "black-2",
      "white",
      "white-2",
      "sword",
      "shield",
      "ultrasun",
      "ultramoon"
    ],
    "isFinalForm": false,
    "evolves_from": null,
    "id": 605
  },
  "beheeyem": {
    "availableEarly": false,
    "isBaseForm": false,
    "isLegendary": false,
    "games": [
      "black",
      "black-2",
      "white",
      "white-2",
      "sword",
      "shield",
      "ultrasun",
      "ultramoon"
    ],
    "isFinalForm": true,
    "evolves_from": "elgyem",
    "id": 606
  },
  "litwick": {
    "availableEarly": false,
    "isBaseForm": true,
    "isLegendary": false,
    "games": [
      "black",
      "black-2",
      "white",
      "white-2",
      "sword",
      "shield"
    ],
    "isFinalForm": false,
    "evolves_from": null,
    "id": 607
  },
  "lampent": {
    "availableEarly": false,
    "isBaseForm": false,
    "isLegendary": false,
    "games": [
      "black",
      "black-2",
      "white",
      "white-2",
      "sword",
      "shield"
    ],
    "isFinalForm": false,
    "evolves_from": "litwick",
    "id": 608
  },
  "chandelure": {
    "availableEarly": false,
    "isBaseForm": false,
    "isLegendary": false,
    "games": [
      "black",
      "black-2",
      "white",
      "white-2",
      "sword",
      "shield"
    ],
    "isFinalForm": true,
    "evolves_from": "lampent",
    "id": 609
  },
  "axew": {
    "availableEarly": false,
    "isBaseForm": true,
    "isLegendary": false,
    "games": [
      "black",
      "black-2",
      "white",
      "white-2",
      "scarlet",
      "violet",
      "sword",
      "shield"
    ],
    "isFinalForm": false,
    "evolves_from": null,
    "id": 610
  },
  "fraxure": {
    "availableEarly": false,
    "isBaseForm": false,
    "isLegendary": false,
    "games": [
      "black",
      "black-2",
      "white",
      "white-2",
      "scarlet",
      "violet",
      "sword",
      "shield"
    ],
    "isFinalForm": false,
    "evolves_from": "axew",
    "id": 611
  },
  "haxorus": {
    "availableEarly": false,
    "isBaseForm": false,
    "isLegendary": false,
    "games": [
      "black",
      "black-2",
      "white",
      "white-2",
      "scarlet",
      "violet",
      "sword",
      "shield"
    ],
    "isFinalForm": true,
    "evolves_from": "fraxure",
    "id": 612
  },
  "cubchoo": {
    "availableEarly": false,
    "isBaseForm": true,
    "isLegendary": false,
    "games": [
      "black",
      "black-2",
      "white",
      "white-2",
      "scarlet",
      "violet",
      "sword",
      "shield"
    ],
    "isFinalForm": false,
    "evolves_from": null,
    "id": 613
  },
  "beartic": {
    "availableEarly": false,
    "isBaseForm": false,
    "isLegendary": false,
    "games": [
      "black",
      "black-2",
      "white",
      "white-2",
      "scarlet",
      "violet",
      "sword",
      "shield"
    ],
    "isFinalForm": true,
    "evolves_from": "cubchoo",
    "id": 614
  },
  "cryogonal": {
    "availableEarly": false,
    "isBaseForm": true,
    "isLegendary": false,
    "games": [
      "black",
      "black-2",
      "white",
      "white-2",
      "scarlet",
      "violet"
    ],
    "isFinalForm": true,
    "evolves_from": null,
    "id": 615
  },
  "shelmet": {
    "availableEarly": false,
    "isBaseForm": true,
    "isLegendary": false,
    "games": [
      "black",
      "black-2",
      "white",
      "white-2",
      "sword",
      "shield"
    ],
    "isFinalForm": false,
    "evolves_from": null,
    "id": 616
  },
  "accelgor": {
    "availableEarly": false,
    "isBaseForm": false,
    "isLegendary": false,
    "games": [
      "black",
      "black-2",
      "white",
      "white-2",
      "sword",
      "shield"
    ],
    "isFinalForm": true,
    "evolves_from": "shelmet",
    "id": 617
  },
  "stunfisk": {
    "availableEarly": false,
    "isBaseForm": true,
    "isLegendary": false,
    "games": [
      "black",
      "black-2",
      "white",
      "white-2",
      "sword",
      "shield"
    ],
    "isFinalForm": true,
    "evolves_from": null,
    "id": 618
  },
  "mienfoo": {
    "availableEarly": false,
    "isBaseForm": true,
    "isLegendary": false,
    "games": [
      "black",
      "black-2",
      "white",
      "white-2",
      "ultrasun",
      "ultramoon"
    ],
    "isFinalForm": false,
    "evolves_from": null,
    "id": 619
  },
  "mienshao": {
    "availableEarly": false,
    "isBaseForm": false,
    "isLegendary": false,
    "games": [
      "black",
      "black-2",
      "white",
      "white-2",
      "ultrasun",
      "ultramoon"
    ],
    "isFinalForm": true,
    "evolves_from": "mienfoo",
    "id": 620
  },
  "druddigon": {
    "availableEarly": false,
    "isBaseForm": true,
    "isLegendary": false,
    "games": [
      "black",
      "black-2",
      "white",
      "white-2",
      "ultrasun",
      "ultramoon"
    ],
    "isFinalForm": true,
    "evolves_from": null,
    "id": 621
  },
  "golett": {
    "availableEarly": false,
    "isBaseForm": true,
    "isLegendary": false,
    "games": [
      "black",
      "black-2",
      "white",
      "white-2",
      "sword",
      "shield",
      "ultrasun",
      "ultramoon"
    ],
    "isFinalForm": false,
    "evolves_from": null,
    "id": 622
  },
  "golurk": {
    "availableEarly": false,
    "isBaseForm": false,
    "isLegendary": false,
    "games": [
      "black",
      "black-2",
      "white",
      "white-2",
      "sword",
      "shield",
      "ultrasun",
      "ultramoon"
    ],
    "isFinalForm": true,
    "evolves_from": "golett",
    "id": 623
  },
  "pawniard": {
    "availableEarly": false,
    "isBaseForm": true,
    "isLegendary": false,
    "games": [
      "black",
      "black-2",
      "white",
      "white-2",
      "scarlet",
      "violet",
      "sword",
      "shield",
      "ultrasun",
      "ultramoon"
    ],
    "isFinalForm": false,
    "evolves_from": null,
    "id": 624
  },
  "bisharp": {
    "availableEarly": false,
    "isBaseForm": false,
    "isLegendary": false,
    "games": [
      "black",
      "black-2",
      "white",
      "white-2",
      "scarlet",
      "violet",
      "sword",
      "shield",
      "ultrasun",
      "ultramoon"
    ],
    "isFinalForm": false,
    "evolves_from": "pawniard",
    "id": 625
  },
  "bouffalant": {
    "availableEarly": false,
    "isBaseForm": true,
    "isLegendary": false,
    "games": [
      "black",
      "black-2",
      "white",
      "white-2"
    ],
    "isFinalForm": true,
    "evolves_from": null,
    "id": 626
  },
  "rufflet": {
    "availableEarly": false,
    "isBaseForm": true,
    "isLegendary": false,
    "games": [
      "black",
      "black-2",
      "white",
      "white-2",
      "scarlet",
      "violet",
      "sword",
      "shield",
      "ultrasun",
      "ultramoon",
      "legendsarceus"
    ],
    "isFinalForm": false,
    "evolves_from": null,
    "id": 627
  },
  "braviary": {
    "availableEarly": false,
    "isBaseForm": false,
    "isLegendary": false,
    "games": [
      "black",
      "black-2",
      "white",
      "white-2",
      "scarlet",
      "violet",
      "sword",
      "shield",
      "ultrasun",
      "ultramoon",
      "legendsarceus"
    ],
    "isFinalForm": true,
    "evolves_from": "rufflet",
    "id": 628
  },
  "vullaby": {
    "availableEarly": false,
    "isBaseForm": true,
    "isLegendary": false,
    "games": [
      "black",
      "black-2",
      "white",
      "white-2",
      "sword",
      "shield",
      "ultrasun",
      "ultramoon"
    ],
    "isFinalForm": false,
    "evolves_from": null,
    "id": 629
  },
  "mandibuzz": {
    "availableEarly": false,
    "isBaseForm": false,
    "isLegendary": false,
    "games": [
      "black",
      "black-2",
      "white",
      "white-2",
      "sword",
      "shield",
      "ultrasun",
      "ultramoon"
    ],
    "isFinalForm": true,
    "evolves_from": "vullaby",
    "id": 630
  },
  "heatmor": {
    "availableEarly": false,
    "isBaseForm": true,
    "isLegendary": false,
    "games": [
      "black",
      "black-2",
      "white",
      "white-2",
      "sword",
      "shield"
    ],
    "isFinalForm": true,
    "evolves_from": null,
    "id": 631
  },
  "durant": {
    "availableEarly": false,
    "isBaseForm": true,
    "isLegendary": false,
    "games": [
      "black",
      "black-2",
      "white",
      "white-2",
      "sword",
      "shield"
    ],
    "isFinalForm": true,
    "evolves_from": null,
    "id": 632
  },
  "deino": {
    "availableEarly": false,
    "isBaseForm": true,
    "isLegendary": false,
    "games": [
      "black",
      "black-2",
      "white",
      "white-2",
      "scarlet",
      "violet",
      "sword",
      "shield"
    ],
    "isFinalForm": false,
    "evolves_from": null,
    "id": 633
  },
  "zweilous": {
    "availableEarly": false,
    "isBaseForm": false,
    "isLegendary": false,
    "games": [
      "black",
      "black-2",
      "white",
      "white-2",
      "scarlet",
      "violet",
      "sword",
      "shield"
    ],
    "isFinalForm": false,
    "evolves_from": "deino",
    "id": 634
  },
  "hydreigon": {
    "availableEarly": false,
    "isBaseForm": false,
    "isLegendary": false,
    "games": [
      "black",
      "black-2",
      "white",
      "white-2",
      "scarlet",
      "violet",
      "sword",
      "shield"
    ],
    "isFinalForm": true,
    "evolves_from": "zweilous",
    "id": 635
  },
  "larvesta": {
    "availableEarly": false,
    "isBaseForm": true,
    "isLegendary": false,
    "games": [
      "black",
      "black-2",
      "white",
      "white-2",
      "scarlet",
      "violet",
      "ultrasun",
      "ultramoon"
    ],
    "isFinalForm": false,
    "evolves_from": null,
    "id": 636
  },
  "volcarona": {
    "availableEarly": false,
    "isBaseForm": false,
    "isLegendary": false,
    "games": [
      "black",
      "black-2",
      "white",
      "white-2",
      "scarlet",
      "violet",
      "ultrasun",
      "ultramoon"
    ],
    "isFinalForm": true,
    "evolves_from": "larvesta",
    "id": 637
  },
  "cobalion": {
    "availableEarly": false,
    "isBaseForm": true,
    "isLegendary": true,
    "games": [
      "black",
      "black-2",
      "white",
      "white-2"
    ],
    "isFinalForm": true,
    "evolves_from": null,
    "id": 638
  },
  "terrakion": {
    "availableEarly": false,
    "isBaseForm": true,
    "isLegendary": true,
    "games": [
      "black",
      "black-2",
      "white",
      "white-2"
    ],
    "isFinalForm": true,
    "evolves_from": null,
    "id": 639
  },
  "virizion": {
    "availableEarly": false,
    "isBaseForm": true,
    "isLegendary": true,
    "games": [
      "black",
      "black-2",
      "white",
      "white-2"
    ],
    "isFinalForm": true,
    "evolves_from": null,
    "id": 640
  },
  "tornadus": {
    "availableEarly": false,
    "isBaseForm": true,
    "isLegendary": true,
    "games": [
      "legendsarceus"
    ],
    "isFinalForm": true,
    "evolves_from": null,
    "id": 641
  },
  "thundurus": {
    "availableEarly": false,
    "isBaseForm": true,
    "isLegendary": true,
    "games": [
      "legendsarceus"
    ],
    "isFinalForm": true,
    "evolves_from": null,
    "id": 642
  },
  "reshiram": {
    "availableEarly": false,
    "isBaseForm": true,
    "isLegendary": true,
    "games": [
      "black",
      "black-2",
      "white",
      "white-2"
    ],
    "isFinalForm": true,
    "evolves_from": null,
    "id": 643
  },
  "zekrom": {
    "availableEarly": false,
    "isBaseForm": true,
    "isLegendary": true,
    "games": [
      "black",
      "black-2",
      "white",
      "white-2"
    ],
    "isFinalForm": true,
    "evolves_from": null,
    "id": 644
  },
  "landorus": {
    "availableEarly": false,
    "isBaseForm": true,
    "isLegendary": true,
    "games": [
      "legendsarceus"
    ],
    "isFinalForm": true,
    "evolves_from": null,
    "id": 645
  },
  "kyurem": {
    "availableEarly": false,
    "isBaseForm": true,
    "isLegendary": true,
    "games": [
      "black",
      "black-2",
      "white",
      "white-2"
    ],
    "isFinalForm": true,
    "evolves_from": null,
    "id": 646
  },
  "keldeo": {
    "availableEarly": false,
    "isBaseForm": true,
    "isLegendary": false,
    "games": [],
    "isFinalForm": true,
    "evolves_from": null,
    "id": 647
  },
  "meloetta": {
    "availableEarly": false,
    "isBaseForm": true,
    "isLegendary": false,
    "games": [],
    "isFinalForm": true,
    "evolves_from": null,
    "id": 648
  },
  "genesect": {
    "availableEarly": false,
    "isBaseForm": true,
    "isLegendary": false,
    "games": [
      "black",
      "black-2",
      "white",
      "white-2"
    ],
    "isFinalForm": true,
    "evolves_from": null,
    "id": 649
  }
}